{
  "archive_url": "https://web.archive.org/web/20201130051600/https://sluga-narodu.com/join/",
  "original_url": "https://sluga-narodu.com/join/",
  "timestamp": "20201130051600",
  "title": "Приєднатися | Політична партія «Слуга Народу»",
  "content_length": 49936,
  "content_length_mb": 0.048,
  "depth": 4,
  "links_found": 45,
  "images_found": 9,
  "processed_at": 1753384334.022961,
  "response_time_ms": 200.29,
  "domain": "sluga-narodu.com",
  "saved_at": "2025-07-24T22:12:14.023655",
  "file_path": "snapshots/sluga_narodu_com/20201130051600/sluga-narodu.com_join_.html"
}